CocoaGUI.py
cocoagui-1.2.0.dist-info/licenses/LICENSE
cocoagui-1.2.0.dist-info/METADATA
cocoagui-1.2.0.dist-info/WHEEL
cocoagui-1.2.0.dist-info/top_level.txt
cocoagui-1.2.0.dist-info/RECORD
